tests/__init__.py
tests/test_add_node.py
tests/test_clone_graph.py
tests/test_create_collection.py
tests/test_create_group.py
tests/test_delete_link.py
tests/test_delete_node.py
tests/test_expand.py
tests/test_has_node.py
tests/test_helpers.py
tests/test_link.py
tests/test_load_graph.py
tests/test_save_graph.py
tests/test_search.py
tests/test_viewers_editors.py
vt_graph_api/__init__.py
vt_graph_api/errors.py
vt_graph_api/graph.py
vt_graph_api/helpers.py
vt_graph_api/node.py
vt_graph_api/version.py
vt_graph_api-2.2.0.dist-info/LICENSE.md
vt_graph_api-2.2.0.dist-info/METADATA
vt_graph_api-2.2.0.dist-info/WHEEL
vt_graph_api-2.2.0.dist-info/top_level.txt
vt_graph_api-2.2.0.dist-info/RECORD
