Metadata-Version: 2.1
Name: vt-graph-api
Version: 2.2.0
Summary: The official Python client library for VirusTotal Graph API
Home-page: https://github.com/virustotal/vt-graph-api
Author: VirusTotal
Author-email: vt_graph_api@virustotal.com
License: Apache 2
Classifier: Programming Language :: Python :: 3
Classifier: License :: OSI Approved :: MIT License
Classifier: Operating System :: OS Independent
License-File: LICENSE.md
Requires-Dist: requests
Requires-Dist: six
